griddb_python/__init__.py
griddb_python/griddb_python.py
griddb_python-5.8.0.dist-info/licenses/LICENSE
griddb_python-5.8.0.dist-info/METADATA
griddb_python-5.8.0.dist-info/WHEEL
griddb_python-5.8.0.dist-info/top_level.txt
griddb_python-5.8.0.dist-info/RECORD
