Metadata-Version: 2.4
Name: griddb_python
Version: 5.8.0
Summary: Python client for GridDB
Author-email: Toshiba Digital Solutions Corporation <contact@griddb.org>
License-Expression: Apache-2.0
Project-URL: Homepage, https://github.com/griddb/python_client
Classifier: Programming Language :: Python :: 3
Classifier: Operating System :: OS Independent
Requires-Python: >=3.9
License-File: LICENSE
Requires-Dist: jpype1
Requires-Dist: pyarrow
Dynamic: license-file
